redditadmin/__init__.py
redditadmin/core.py
redditadmin/__tests__/__init__.py
redditadmin/__tests__/test_core.py
redditadmin/plugintools/__init__.py
redditadmin/plugintools/asynchronouspluginsexecutor.py
redditadmin/plugintools/plugin.py
redditadmin/plugintools/pluginsexecutor.py
redditadmin/plugintools/redditinterfacefactory.py
redditadmin/plugintools/__tests__/__init__.py
redditadmin/plugintools/__tests__/test_asynchronouspluginsexecutor.py
redditadmin/plugintools/__tests__/test_plugin.py
redditadmin/plugintools/__tests__/test_pluginsexecutor.py
redditadmin/plugintools/__tests__/test_redditinterfacefactory.py
redditadmin/program/__init__.py
redditadmin/program/program.py
redditadmin/program/streamprocessingprogram.py
redditadmin/program/__tests__/__init__.py
redditadmin/program/__tests__/test_program.py
redditadmin/program/__tests__/test_streamprocessingprogram.py
redditadmin/utility/__init__.py
redditadmin/utility/botcredentials.py
redditadmin/utility/contributions.py
redditadmin/utility/decorators.py
redditadmin/utility/miscellaneous.py
redditadmin/utility/redditinterface.py
redditadmin/utility/redditsubmission.py
redditadmin/utility/__tests__/__init__.py
redditadmin/utility/__tests__/test_contributions.py
redditadmin/utility/__tests__/test_decorators.py
redditadmin/utility/__tests__/test_miscellaneous.py
redditadmin/utility/__tests__/test_redditsubmission.py
redditadmin-0.1.7.dist-info/METADATA
redditadmin-0.1.7.dist-info/WHEEL
redditadmin-0.1.7.dist-info/licenses/LICENSE
redditadmin-0.1.7.dist-info/RECORD
