Metadata-Version: 2.4
Name: redditadmin
Version: 0.1.7
Summary: Extensible Python administrative bot
Project-URL: Homepage, https://github.com/Grod56/reddit-admin
Project-URL: Issues, https://github.com/Grod56/reddit-admin/issues
Author-email: Grod56 <providenceuniversalstudios@gmail.com>
License-Expression: MIT
License-File: LICENSE
Classifier: Operating System :: OS Independent
Classifier: Programming Language :: Python :: 3
Requires-Python: >=3.11
